kattis_tracker_py/__init__.py
kattis_tracker_py/client.py
kattis_tracker_py-1.1.0.dist-info/METADATA
kattis_tracker_py-1.1.0.dist-info/WHEEL
kattis_tracker_py-1.1.0.dist-info/licenses/LICENSE.md
kattis_tracker_py-1.1.0.dist-info/RECORD
